labelformat/__init__.py
labelformat/cli/cli.py
labelformat/cli/registry.py
labelformat/errors.py
labelformat/formats/__init__.py
labelformat/formats/coco.py
labelformat/formats/coco_segmentation_helpers.py
labelformat/formats/cvat.py
labelformat/formats/kitti.py
labelformat/formats/labelbox.py
labelformat/formats/labelformat.py
labelformat/formats/lightly.py
labelformat/formats/maskpair.py
labelformat/formats/pascalvoc.py
labelformat/formats/rtdetr.py
labelformat/formats/rtdetrv2.py
labelformat/formats/semantic_segmentation/pascalvoc.py
labelformat/formats/yolov10.py
labelformat/formats/yolov11.py
labelformat/formats/yolov12.py
labelformat/formats/yolov26.py
labelformat/formats/yolov5.py
labelformat/formats/yolov6.py
labelformat/formats/yolov7.py
labelformat/formats/yolov8.py
labelformat/formats/yolov9.py
labelformat/formats/youtubevis.py
labelformat/mask_utils.py
labelformat/model/__init__.py
labelformat/model/binary_mask_segmentation.py
labelformat/model/bounding_box.py
labelformat/model/category.py
labelformat/model/image.py
labelformat/model/instance_segmentation.py
labelformat/model/instance_segmentation_track.py
labelformat/model/multipolygon.py
labelformat/model/object_detection.py
labelformat/model/object_detection_track.py
labelformat/model/semantic_segmentation.py
labelformat/model/video.py
labelformat/py.typed
labelformat/types.py
labelformat/utils.py
labelformat-0.1.10.dist-info/METADATA
labelformat-0.1.10.dist-info/WHEEL
labelformat-0.1.10.dist-info/entry_points.txt
labelformat-0.1.10.dist-info/licenses/LICENSE
labelformat-0.1.10.dist-info/RECORD
