Metadata-Version: 2.4
Name: labelformat
Version: 0.1.10
Summary: A tool for converting computer vision label formats.
License: MIT
License-File: LICENSE
Author: Lightly.ai
Requires-Python: >=3.8
Classifier: License :: OSI Approved :: MIT License
Classifier: Programming Language :: Python :: 3
Classifier: Programming Language :: Python :: 3.8
Classifier: Programming Language :: Python :: 3.9
Classifier: Programming Language :: Python :: 3.10
Classifier: Programming Language :: Python :: 3.11
Classifier: Programming Language :: Python :: 3.12
Classifier: Programming Language :: Python :: 3.13
Classifier: Programming Language :: Python :: 3.14
Requires-Dist: numpy
Requires-Dist: pillow
Requires-Dist: pydantic-xml
Requires-Dist: pyyaml
Requires-Dist: tqdm
